KratosMultiphysics/FSIApplication/Conformant_OneSideMap.py
KratosMultiphysics/FSIApplication/__init__.py
KratosMultiphysics/FSIApplication/__init__.pyi
KratosMultiphysics/FSIApplication/convergence_accelerator_factory.py
KratosMultiphysics/FSIApplication/fsi_analysis.py
KratosMultiphysics/FSIApplication/fsi_coupling_interface.py
KratosMultiphysics/FSIApplication/partitioned_embedded_fsi_base_solver.py
KratosMultiphysics/FSIApplication/partitioned_fsi_base_solver.py
KratosMultiphysics/FSIApplication/python_solvers_wrapper_fsi.py
KratosMultiphysics/FSIApplication/trilinos_partitioned_fsi_base_solver.py
KratosMultiphysics/.libs/KratosFSIApplication.cpython-38-x86_64-linux-gnu.so
KratosMultiphysics/.libs/libKratosFSICore.so
kratosfsiapplication-10.4.0.dist-info/METADATA
kratosfsiapplication-10.4.0.dist-info/WHEEL
kratosfsiapplication-10.4.0.dist-info/RECORD
